{
  "products": [
    {
      "id": 1,
      "title": "Galaxy S22 Ultra",
      "price": 630,
      "image": "https://api.radius.uz/storage/products/January2025/lersz6ZGnzuc0kZFKS2m.webp",
      "url": "/product/1",
      "categories": ["smartphones", "electronics"]
    },
    {
      "id": 2,
      "title": "Iphone 16",
      "price": 999,
      "image": "https://3dplanet.am/wp-content/uploads/2024/09/16-black.jpg",
      "url": "/product/2",
      "categories": ["smartphones", "electronics"]
    },
    {
      "id": 3,
      "title": "Macbook Pro 16",
      "price": 1999,
      "image": "https://brostore.uz/cdn/shop/files/1_30a83e5f-52d3-4ca7-a682-9d6dfa92cc8b.png?v=1707381920",
      "url": "/product/3",
      "categories": ["laptops", "electronics"]
    }
  ],
  "users": [
    {
      "id": "b270c01f-40cd-4f7a-81a0-9f480d5d14d2",
      "username": "john",
      "password": "1234",
      "cart": [1]
    },
    {
      "id": "29ca657f-1998-4bc0-b5ee-b4522f72bbc7",
      "username": "alex",
      "password": "1234",
      "cart": [1]
    }
  ],
  "admins": [
    {
      "id": 1,
      "username": "admin",
      "password": "admin123"
    }
  ]
}
